{
  "model_type": "gbdt",
  "num_trees": 250,
  "max_depth": 10,
  "learning_rate": 0.03,
  "feature_fraction": 0.75,
  "bagging_fraction": 0.8,
  "num_leaves": 63,
  "early_stopping_rounds": 15,
  "num_boost_round": 200,
  "bagging_freq": 3,
  "objective": "binary",
  "metric": "auc",
  "use_tensorrt": true,
  "use_fp16": true,
  "max_batch_size": 128,
  "model_path": "models/gbdt/v1.0.0/model.pkl",
  "feature_importance_type": "gain",
  "enable_categorical": true,
  "features": [
    "price_rel_open",
    "price_rel_close",
    "price_rel_vwap",
    "day_high_pos",
    "day_low_pos",
    "price_velocity_1m",
    "price_velocity_5m",
    "volume_rel_avg",
    "volume_accel",
    "volume_spike",
    "rsi_9",
    "macd",
    "bb_position",
    "atr_normalized",
    "momentum_1m",
    "sma_cross_signal",
    "support_resistance_proximity",
    "volatility_ratio"
  ]
}